gc_cpm_networks
